mathtypes/__init__.py
mathtypes/main.py
mathtypes-0.1.2.dist-info/METADATA
mathtypes-0.1.2.dist-info/WHEEL
mathtypes-0.1.2.dist-info/top_level.txt
mathtypes-0.1.2.dist-info/RECORD
