Metadata-Version: 2.4
Name: mathtypes
Version: 0.1.2
Summary: A simple package that provides you math types like fraction
Author-email: BK Darsh <darshtyagidt15@email.com>
License: MIT
Requires-Python: >=3.8
